crud/__init__.py
crud/app.py
crud/entities.py
crud/lib.py
kougen_fastapi_crud-1.3.0.dist-info/METADATA
kougen_fastapi_crud-1.3.0.dist-info/WHEEL
kougen_fastapi_crud-1.3.0.dist-info/top_level.txt
kougen_fastapi_crud-1.3.0.dist-info/RECORD
